schwab/__init__.py
schwab/async_client.py
schwab/auth.py
schwab/client.py
schwab/client_advanced_methods.py
schwab/order_management.py
schwab/order_methods.py
schwab/order_monitor.py
schwab/portfolio.py
schwab/streaming.py
schwab/api/__init__.py
schwab/api/quotes.py
schwab/models/__init__.py
schwab/models/base.py
schwab/models/execution.py
schwab/models/order_validation.py
schwab/models/orders.py
schwab/models/quotes.py
schwab/models/generated/__init__.py
schwab/models/generated/market_data_models.py
schwab/models/generated/trading_models.py
schwab/paper_trading/__init__.py
schwab/paper_trading/account.py
schwab/paper_trading/client.py
schwab/paper_trading/indicators.py
schwab/utils/__init__.py
schwab_trader-1.0.0.dist-info/licenses/LICENSE
tests/__init__.py
tests/conftest.py
tests/test_account.py
tests/test_auth.py
tests/test_order_creation.py
tests/test_order_instructions.py
tests/test_order_management.py
tests/test_paper_trading.py
tests/test_portfolio.py
tests/test_quotes.py
tests/helpers/__init__.py
tests/helpers/model_factories.py
schwab_trader-1.0.0.dist-info/METADATA
schwab_trader-1.0.0.dist-info/WHEEL
schwab_trader-1.0.0.dist-info/top_level.txt
schwab_trader-1.0.0.dist-info/RECORD
